[
  {
    "subject": {
      "slug": "nasturtium",
      "name": "Nasturtium",
      "bot": "Tropaeolum",
      "genus": "tropaeolum",
      "cat": "Annual",
      "sun": "full-sun",
      "water": "low",
      "zones": "none",
      "zmin": null,
      "zmax": null,
      "h": 0.3,
      "spread": 0.5,
      "bloom": "6-9",
      "tags": "annual|full sun|summer|fall|orange|edible|drought tolerant",
      "archetype": true
    },
    "candidates": 173,
    "companions": [
      {
        "slug": "rock-cress",
        "name": "Rock Cress",
        "bot": "Aubrieta",
        "genus": "aubrieta",
        "cat": "Perennial",
        "sun": "full-sun",
        "water": "low",
        "zones": "4-8",
        "zmin": 4,
        "zmax": 8,
        "h": 0.1,
        "spread": 0.4,
        "bloom": "4-5",
        "tags": "perennial|full sun|spring|purple|edging|drought tolerant",
        "archetype": true,
        "score": 64.4,
        "reason": "Shares full sun and low water; blooms in mid spring, before this one opens; evergreen, so the bed keeps its shape through winter; lower at 0.1 m, for the front of the border.",
        "penalties": [
          "over-recommended"
        ]
      },
      {
        "slug": "rosemary",
        "name": "Rosemary",
        "bot": "Salvia rosmarinus",
        "genus": "salvia",
        "cat": "Herb",
        "sun": "full-sun",
        "water": "low",
        "zones": "7-10",
        "zmin": 7,
        "zmax": 10,
        "h": 1,
        "spread": 0.8,
        "bloom": "3-5",
        "tags": "herb|full sun|spring|blue|fragrant|edible|evergreen|drought tolerant",
        "archetype": true,
        "score": 62.7,
        "reason": "Shares full sun and low water; blooms in early spring, before this one opens; both offer pollinator forage, in different months; evergreen, so the bed keeps its shape through winter.",
        "penalties": [
          "over-recommended"
        ]
      },
      {
        "slug": "sea-thrift",
        "name": "Sea Thrift",
        "bot": "Armeria maritima",
        "genus": "armeria",
        "cat": "Perennial",
        "sun": "full-sun",
        "water": "low",
        "zones": "4-8",
        "zmin": 4,
        "zmax": 8,
        "h": 0.2,
        "spread": 0.3,
        "bloom": "4-6",
        "tags": "perennial|full sun|spring|summer|pink|edging|drought tolerant",
        "archetype": true,
        "score": 60.5,
        "reason": "Shares full sun and low water; opens in mid spring and overlaps into this one's season; evergreen, so the bed keeps its shape through winter; lower at 0.2 m, for the front of the border.",
        "penalties": [
          "over-recommended"
        ]
      },
      {
        "slug": "echinops",
        "name": "Globe Thistle",
        "bot": "Echinops",
        "genus": "echinops",
        "cat": "Perennial",
        "sun": "full-sun",
        "water": "low",
        "zones": "3-9",
        "zmin": 3,
        "zmax": 9,
        "h": 1,
        "spread": 0.6,
        "bloom": "7-8",
        "tags": "perennial|full sun|summer|blue|architectural|pollinator|drought tolerant",
        "archetype": true,
        "score": 60.3,
        "reason": "Shares full sun and low water; its seed heads stand through winter, for structure and the birds; both offer pollinator forage; taller at 1 m, for the layer behind it.",
        "penalties": []
      },
      {
        "slug": "fountain-grass",
        "name": "Fountain Grass",
        "bot": "Pennisetum alopecuroides",
        "genus": "pennisetum",
        "cat": "Grass",
        "sun": "full-sun",
        "water": "low",
        "zones": "5-9",
        "zmin": 5,
        "zmax": 9,
        "h": 1,
        "spread": 1,
        "bloom": "8-10",
        "tags": "grass|full sun|summer|fall|green|plume|drought tolerant",
        "archetype": true,
        "score": 50.9,
        "reason": "Shares full sun and low water; overlaps, then carries the display into mid fall; its seed heads stand through winter, for structure and the birds; taller at 1 m, for the layer behind it.",
        "penalties": []
      },
      {
        "slug": "switchgrass",
        "name": "Switchgrass",
        "bot": "Panicum virgatum",
        "genus": "panicum",
        "cat": "Grass",
        "sun": "full-sun",
        "water": "low",
        "zones": "4-9",
        "zmin": 4,
        "zmax": 9,
        "h": 1.5,
        "spread": 0.8,
        "bloom": "8-10",
        "tags": "grass|full sun|summer|fall|green|plume|native|drought tolerant",
        "archetype": true,
        "score": 50.6,
        "reason": "Shares full sun and low water; overlaps, then carries the display into mid fall; its seed heads stand through winter, for structure and the birds; taller at 1.5 m, for the layer behind it.",
        "penalties": [
          "over-recommended"
        ]
      },
      {
        "slug": "pampas-grass",
        "name": "Pampas Grass",
        "bot": "Cortaderia selloana",
        "genus": "cortaderia",
        "cat": "Grass",
        "sun": "full-sun",
        "water": "low",
        "zones": "7-11",
        "zmin": 7,
        "zmax": 11,
        "h": 2.5,
        "spread": 1.5,
        "bloom": "8-10",
        "tags": "grass|full sun|summer|fall|plume|white|drought tolerant",
        "archetype": true,
        "score": 50.6,
        "reason": "Shares full sun and low water; overlaps, then carries the display into mid fall; its seed heads stand through winter, for structure and the birds; stands well above at 2.5 m, a canopy to plant beneath.",
        "penalties": []
      },
      {
        "slug": "viburnum",
        "name": "Viburnum",
        "bot": "Viburnum",
        "genus": "viburnum",
        "cat": "Shrub",
        "sun": "full-sun",
        "water": "moderate",
        "zones": "3-8",
        "zmin": 3,
        "zmax": 8,
        "h": 2,
        "spread": 2,
        "bloom": "4-5",
        "tags": "shrub|full sun|spring|white|fragrant",
        "archetype": true,
        "score": 49.3,
        "reason": "Shares full sun and low to moderate water; blooms in mid spring, before this one opens; stands well above at 2 m, a canopy to plant beneath; both offer pollinator forage, in different months.",
        "penalties": [
          "water-differs",
          "over-recommended"
        ]
      }
    ]
  },
  {
    "subject": {
      "slug": "new-dawn-rose",
      "name": "New Dawn",
      "bot": "Rosa 'New Dawn'",
      "genus": "rosa",
      "cat": "Rose",
      "sun": "full-sun",
      "water": "moderate",
      "zones": "5-9",
      "zmin": 5,
      "zmax": 9,
      "h": 3.5,
      "spread": 2.5,
      "bloom": "5-10",
      "tags": "rose|full sun|spring|summer|fall|pink|fragrant|climbing|classic",
      "archetype": true
    },
    "candidates": 180,
    "companions": [
      {
        "slug": "bergenia",
        "name": "Bergenia",
        "bot": "Bergenia",
        "genus": "bergenia",
        "cat": "Perennial",
        "sun": "part-sun",
        "water": "moderate",
        "zones": "3-8",
        "zmin": 3,
        "zmax": 8,
        "h": 0.4,
        "spread": 0.5,
        "bloom": "4-5",
        "tags": "perennial|partial sun|spring|pink|foliage|evergreen",
        "archetype": true,
        "score": 55.7,
        "reason": "Takes full sun to part sun and moderate water; opens in mid spring and overlaps into this one's season; evergreen, so the bed keeps its shape through winter; a soft colour beside the pink.",
        "penalties": [
          "over-recommended"
        ]
      },
      {
        "slug": "aster",
        "name": "Aster",
        "bot": "Symphyotrichum",
        "genus": "symphyotrichum",
        "cat": "Perennial",
        "sun": "full-sun",
        "water": "moderate",
        "zones": "3-8",
        "zmin": 3,
        "zmax": 8,
        "h": 0.9,
        "spread": 0.6,
        "bloom": "9-10",
        "tags": "perennial|full sun|fall|purple|pollinator",
        "archetype": true,
        "score": 52.9,
        "reason": "Shares full sun and moderate water; its seed heads stand through winter, for structure and the birds; lower at 0.9 m, for the front of the border; a soft colour beside the pink.",
        "penalties": [
          "over-recommended"
        ]
      },
      {
        "slug": "liatris",
        "name": "Blazing Star",
        "bot": "Liatris",
        "genus": "liatris",
        "cat": "Perennial",
        "sun": "full-sun",
        "water": "low",
        "zones": "3-9",
        "zmin": 3,
        "zmax": 9,
        "h": 0.9,
        "spread": 0.3,
        "bloom": "7-8",
        "tags": "perennial|full sun|summer|purple|pollinator|native|drought tolerant",
        "archetype": true,
        "score": 52.2,
        "reason": "Shares full sun and low to moderate water; its seed heads stand through winter, for structure and the birds; lower at 0.9 m, for the front of the border; a soft colour beside the pink.",
        "penalties": [
          "water-differs"
        ]
      },
      {
        "slug": "maiden-grass",
        "name": "Maiden Grass",
        "bot": "Miscanthus sinensis",
        "genus": "miscanthus",
        "cat": "Grass",
        "sun": "full-sun",
        "water": "low",
        "zones": "5-9",
        "zmin": 5,
        "zmax": 9,
        "h": 1.8,
        "spread": 1.2,
        "bloom": "9-10",
        "tags": "grass|full sun|fall|plume|silver|drought tolerant",
        "archetype": true,
        "score": 49.8,
        "reason": "Shares full sun and low to moderate water; its seed heads stand through winter, for structure and the birds; lower at 1.8 m, for the front of the border; a soft colour beside the pink.",
        "penalties": [
          "water-differs"
        ]
      },
      {
        "slug": "blue-oat-grass",
        "name": "Blue Oat Grass",
        "bot": "Helictotrichon sempervirens",
        "genus": "helictotrichon",
        "cat": "Grass",
        "sun": "full-sun",
        "water": "low",
        "zones": "4-9",
        "zmin": 4,
        "zmax": 9,
        "h": 0.7,
        "spread": 0.6,
        "bloom": "6-7",
        "tags": "grass|full sun|summer|blue|evergreen|drought tolerant",
        "archetype": true,
        "score": 48.9,
        "reason": "Shares full sun and low to moderate water; evergreen, so the bed keeps its shape through winter; lower at 0.7 m, for the front of the border; a soft colour beside the pink.",
        "penalties": [
          "water-differs",
          "over-recommended"
        ]
      },
      {
        "slug": "feather-reed-grass",
        "name": "Feather Reed Grass",
        "bot": "Calamagrostis × acutiflora",
        "genus": "calamagrostis",
        "cat": "Grass",
        "sun": "full-sun",
        "water": "moderate",
        "zones": "4-9",
        "zmin": 4,
        "zmax": 9,
        "h": 1.5,
        "spread": 0.6,
        "bloom": "6-8",
        "tags": "grass|full sun|summer|green|plume|vertical",
        "archetype": true,
        "score": 48.6,
        "reason": "Shares full sun and moderate water; its seed heads stand through winter, for structure and the birds; lower at 1.5 m, for the front of the border; a soft colour beside the pink.",
        "penalties": [
          "over-recommended"
        ]
      },
      {
        "slug": "forsythia",
        "name": "Forsythia",
        "bot": "Forsythia",
        "genus": "forsythia",
        "cat": "Shrub",
        "sun": "full-sun",
        "water": "moderate",
        "zones": "5-8",
        "zmin": 5,
        "zmax": 8,
        "h": 2,
        "spread": 2,
        "bloom": "3-4",
        "tags": "shrub|full sun|spring|yellow|early",
        "archetype": true,
        "score": 47.2,
        "reason": "Shares full sun and moderate water; blooms in early spring, before this one opens; lower at 2 m, for the front of the border; a soft colour beside the pink.",
        "penalties": []
      },
      {
        "slug": "rosemary",
        "name": "Rosemary",
        "bot": "Salvia rosmarinus",
        "genus": "salvia",
        "cat": "Herb",
        "sun": "full-sun",
        "water": "low",
        "zones": "7-10",
        "zmin": 7,
        "zmax": 10,
        "h": 1,
        "spread": 0.8,
        "bloom": "3-5",
        "tags": "herb|full sun|spring|blue|fragrant|edible|evergreen|drought tolerant",
        "archetype": true,
        "score": 45,
        "reason": "Shares full sun and low to moderate water; opens in early spring and overlaps into this one's season; evergreen, so the bed keeps its shape through winter; lower at 1 m, for the front of the border.",
        "penalties": [
          "water-differs",
          "over-recommended"
        ]
      }
    ]
  },
  {
    "subject": {
      "slug": "nicotiana",
      "name": "Flowering Tobacco",
      "bot": "Nicotiana",
      "genus": "nicotiana",
      "cat": "Annual",
      "sun": "part-sun",
      "water": "moderate",
      "zones": "10-11",
      "zmin": 10,
      "zmax": 11,
      "h": 0.6,
      "spread": 0.3,
      "bloom": "6-9",
      "tags": "annual|partial sun|summer|fall|white|fragrant",
      "archetype": true
    },
    "candidates": 238,
    "companions": [
      {
        "slug": "perennial-sunflower",
        "name": "Perennial Sunflower",
        "bot": "Helianthus",
        "genus": "helianthus",
        "cat": "Perennial",
        "sun": "full-sun",
        "water": "moderate",
        "zones": "4-9",
        "zmin": 4,
        "zmax": 9,
        "h": 1.5,
        "spread": 0.8,
        "bloom": "8-10",
        "tags": "perennial|full sun|summer|fall|yellow|pollinator|native|tall",
        "archetype": true,
        "score": 62.5,
        "reason": "Takes full sun to part sun and moderate water; overlaps, then carries the display into mid fall; its seed heads stand through winter, for structure and the birds; both offer pollinator forage.",
        "penalties": [
          "over-recommended"
        ]
      },
      {
        "slug": "aster",
        "name": "Aster",
        "bot": "Symphyotrichum",
        "genus": "symphyotrichum",
        "cat": "Perennial",
        "sun": "full-sun",
        "water": "moderate",
        "zones": "3-8",
        "zmin": 3,
        "zmax": 8,
        "h": 0.9,
        "spread": 0.6,
        "bloom": "9-10",
        "tags": "perennial|full sun|fall|purple|pollinator",
        "archetype": true,
        "score": 61.7,
        "reason": "Takes full sun to part sun and moderate water; overlaps, then carries the display into mid fall; its seed heads stand through winter, for structure and the birds; both offer pollinator forage.",
        "penalties": [
          "over-recommended"
        ]
      },
      {
        "slug": "rock-cress",
        "name": "Rock Cress",
        "bot": "Aubrieta",
        "genus": "aubrieta",
        "cat": "Perennial",
        "sun": "full-sun",
        "water": "low",
        "zones": "4-8",
        "zmin": 4,
        "zmax": 8,
        "h": 0.1,
        "spread": 0.4,
        "bloom": "4-5",
        "tags": "perennial|full sun|spring|purple|edging|drought tolerant",
        "archetype": true,
        "score": 61.2,
        "reason": "Takes full sun to part sun and low to moderate water; blooms in mid spring, before this one opens; evergreen, so the bed keeps its shape through winter; lower at 0.1 m, for the front of the border.",
        "penalties": [
          "water-differs",
          "over-recommended"
        ]
      },
      {
        "slug": "azalea",
        "name": "Azalea",
        "bot": "Rhododendron",
        "genus": "rhododendron",
        "cat": "Shrub",
        "sun": "part-shade",
        "water": "moderate",
        "zones": "5-9",
        "zmin": 5,
        "zmax": 9,
        "h": 1.2,
        "spread": 1.2,
        "bloom": "4-5",
        "tags": "shrub|part shade|spring|pink",
        "archetype": true,
        "score": 58.1,
        "reason": "Takes part sun to part shade and moderate water; blooms in mid spring, before this one opens; evergreen, so the bed keeps its shape through winter; taller at 1.2 m, for the layer behind it.",
        "penalties": [
          "over-recommended"
        ]
      },
      {
        "slug": "rosemary",
        "name": "Rosemary",
        "bot": "Salvia rosmarinus",
        "genus": "salvia",
        "cat": "Herb",
        "sun": "full-sun",
        "water": "low",
        "zones": "7-10",
        "zmin": 7,
        "zmax": 10,
        "h": 1,
        "spread": 0.8,
        "bloom": "3-5",
        "tags": "herb|full sun|spring|blue|fragrant|edible|evergreen|drought tolerant",
        "archetype": true,
        "score": 57.7,
        "reason": "Takes full sun to part sun and low to moderate water; blooms in early spring, before this one opens; both offer pollinator forage, in different months; evergreen, so the bed keeps its shape through winter.",
        "penalties": [
          "water-differs",
          "over-recommended"
        ]
      },
      {
        "slug": "crabapple",
        "name": "Flowering Crabapple",
        "bot": "Malus",
        "genus": "malus",
        "cat": "Tree",
        "sun": "full-sun",
        "water": "moderate",
        "zones": "4-8",
        "zmin": 4,
        "zmax": 8,
        "h": 6,
        "spread": 6,
        "bloom": "4-5",
        "tags": "tree|full sun|spring|pink|berries",
        "archetype": true,
        "score": 57.4,
        "reason": "Takes full sun to part sun and moderate water; blooms in mid spring, before this one opens; both offer pollinator forage, in different months; a soft colour beside the pink.",
        "penalties": [
          "over-recommended"
        ]
      },
      {
        "slug": "lilac",
        "name": "Lilac",
        "bot": "Syringa vulgaris",
        "genus": "syringa",
        "cat": "Shrub",
        "sun": "full-sun",
        "water": "moderate",
        "zones": "3-7",
        "zmin": 3,
        "zmax": 7,
        "h": 3,
        "spread": 2.5,
        "bloom": "4-5",
        "tags": "shrub|full sun|spring|purple|fragrant",
        "archetype": true,
        "score": 55.3,
        "reason": "Takes full sun to part sun and moderate water; blooms in mid spring, before this one opens; taller at 3 m, for the layer behind it; both offer pollinator forage, in different months.",
        "penalties": []
      },
      {
        "slug": "viburnum",
        "name": "Viburnum",
        "bot": "Viburnum",
        "genus": "viburnum",
        "cat": "Shrub",
        "sun": "full-sun",
        "water": "moderate",
        "zones": "3-8",
        "zmin": 3,
        "zmax": 8,
        "h": 2,
        "spread": 2,
        "bloom": "4-5",
        "tags": "shrub|full sun|spring|white|fragrant",
        "archetype": true,
        "score": 53.6,
        "reason": "Takes full sun to part sun and moderate water; blooms in mid spring, before this one opens; taller at 2 m, for the layer behind it; both offer pollinator forage, in different months.",
        "penalties": [
          "over-recommended"
        ]
      }
    ]
  },
  {
    "subject": {
      "slug": "ninebark",
      "name": "Ninebark",
      "bot": "Physocarpus opulifolius",
      "genus": "physocarpus",
      "cat": "Shrub",
      "sun": "full-sun",
      "water": "moderate",
      "zones": "3-7",
      "zmin": 3,
      "zmax": 7,
      "h": 2,
      "spread": 2,
      "bloom": "5-6",
      "tags": "shrub|full sun|spring|summer|white|foliage|native",
      "archetype": true
    },
    "candidates": 191,
    "companions": [
      {
        "slug": "black-eyed-susan",
        "name": "Black-Eyed Susan",
        "bot": "Rudbeckia",
        "genus": "rudbeckia",
        "cat": "Perennial",
        "sun": "full-sun",
        "water": "low",
        "zones": "3-9",
        "zmin": 3,
        "zmax": 9,
        "h": 0.8,
        "spread": 0.5,
        "bloom": "7-9",
        "tags": "perennial|full sun|summer|fall|yellow|pollinator|native|drought tolerant",
        "archetype": true,
        "score": 62.8,
        "reason": "Shares full sun and low to moderate water; blooms in midsummer as this one finishes; its seed heads stand through winter, for structure and the birds; lower at 0.8 m, for the front of the border.",
        "penalties": [
          "water-differs"
        ]
      },
      {
        "slug": "coneflower",
        "name": "Purple Coneflower",
        "bot": "Echinacea purpurea",
        "genus": "echinacea",
        "cat": "Perennial",
        "sun": "full-sun",
        "water": "low",
        "zones": "3-9",
        "zmin": 3,
        "zmax": 9,
        "h": 0.9,
        "spread": 0.5,
        "bloom": "7-9",
        "tags": "perennial|full sun|summer|fall|pink|pollinator|native|drought tolerant",
        "archetype": true,
        "score": 62.8,
        "reason": "Shares full sun and low to moderate water; blooms in midsummer as this one finishes; its seed heads stand through winter, for structure and the birds; lower at 0.9 m, for the front of the border.",
        "penalties": [
          "water-differs"
        ]
      },
      {
        "slug": "liatris",
        "name": "Blazing Star",
        "bot": "Liatris",
        "genus": "liatris",
        "cat": "Perennial",
        "sun": "full-sun",
        "water": "low",
        "zones": "3-9",
        "zmin": 3,
        "zmax": 9,
        "h": 0.9,
        "spread": 0.3,
        "bloom": "7-8",
        "tags": "perennial|full sun|summer|purple|pollinator|native|drought tolerant",
        "archetype": true,
        "score": 62.8,
        "reason": "Shares full sun and low to moderate water; blooms in midsummer as this one finishes; its seed heads stand through winter, for structure and the birds; lower at 0.9 m, for the front of the border.",
        "penalties": [
          "water-differs"
        ]
      },
      {
        "slug": "scilla",
        "name": "Siberian Squill",
        "bot": "Scilla siberica",
        "genus": "scilla",
        "cat": "Bulb",
        "sun": "full-sun",
        "water": "moderate",
        "zones": "2-8",
        "zmin": 2,
        "zmax": 8,
        "h": 0.15,
        "spread": 0.08,
        "bloom": "3-4",
        "tags": "bulb|full sun|spring|blue|early",
        "archetype": true,
        "score": 59.5,
        "reason": "Shares full sun and moderate water; blooms in early spring, before this one opens; low at 0.15 m, to carpet the ground beneath; a soft colour beside the pink.",
        "penalties": []
      },
      {
        "slug": "windflower",
        "name": "Windflower",
        "bot": "Anemone blanda",
        "genus": "anemone",
        "cat": "Bulb",
        "sun": "part-sun",
        "water": "moderate",
        "zones": "4-8",
        "zmin": 4,
        "zmax": 8,
        "h": 0.15,
        "spread": 0.1,
        "bloom": "3-4",
        "tags": "bulb|partial sun|spring|blue|early",
        "archetype": true,
        "score": 59.5,
        "reason": "Takes full sun to part sun and moderate water; blooms in early spring, before this one opens; low at 0.15 m, to carpet the ground beneath; a soft colour beside the pink.",
        "penalties": []
      },
      {
        "slug": "hyacinth",
        "name": "Hyacinth",
        "bot": "Hyacinthus orientalis",
        "genus": "hyacinthus",
        "cat": "Bulb",
        "sun": "full-sun",
        "water": "moderate",
        "zones": "4-8",
        "zmin": 4,
        "zmax": 8,
        "h": 0.25,
        "spread": 0.12,
        "bloom": "3-4",
        "tags": "bulb|full sun|spring|blue|fragrant",
        "archetype": true,
        "score": 56.4,
        "reason": "Shares full sun and moderate water; blooms in early spring, before this one opens; low at 0.25 m, to carpet the ground beneath; a soft colour beside the pink.",
        "penalties": [
          "over-recommended"
        ]
      },
      {
        "slug": "arborvitae",
        "name": "Arborvitae",
        "bot": "Thuja occidentalis",
        "genus": "thuja",
        "cat": "Conifer",
        "sun": "full-sun",
        "water": "moderate",
        "zones": "3-8",
        "zmin": 3,
        "zmax": 8,
        "h": 6,
        "spread": 1.5,
        "bloom": "",
        "tags": "conifer|full sun|evergreen|columnar|screen|hedge",
        "archetype": true,
        "score": 53.2,
        "reason": "Shares full sun and moderate water; evergreen, so the bed keeps its shape through winter; taller at 6 m, for the layer behind it; both are native plants.",
        "penalties": []
      },
      {
        "slug": "calibrachoa",
        "name": "Calibrachoa",
        "bot": "Calibrachoa",
        "genus": "calibrachoa",
        "cat": "Annual",
        "sun": "full-sun",
        "water": "moderate",
        "zones": "9-11",
        "zmin": 9,
        "zmax": 11,
        "h": 0.2,
        "spread": 0.4,
        "bloom": "5-10",
        "tags": "annual|full sun|spring|summer|fall|orange|trailing|container",
        "archetype": true,
        "score": 51.5,
        "reason": "Shares full sun and moderate water; overlaps, then carries the display into mid fall; low at 0.2 m, to carpet the ground beneath; a soft colour beside the pink.",
        "penalties": []
      }
    ]
  },
  {
    "subject": {
      "slug": "northern-sea-oats",
      "name": "Northern Sea Oats",
      "bot": "Chasmanthium latifolium",
      "genus": "chasmanthium",
      "cat": "Grass",
      "sun": "part-shade",
      "water": "moderate",
      "zones": "3-8",
      "zmin": 3,
      "zmax": 8,
      "h": 1,
      "spread": 0.6,
      "bloom": "7-9",
      "tags": "grass|part shade|summer|fall|green|native|seed heads|shade",
      "archetype": true
    },
    "candidates": 84,
    "companions": [
      {
        "slug": "pansy",
        "name": "Pansy",
        "bot": "Viola × wittrockiana",
        "genus": "viola",
        "cat": "Annual",
        "sun": "part-sun",
        "water": "moderate",
        "zones": "none",
        "zmin": null,
        "zmax": null,
        "h": 0.2,
        "spread": 0.2,
        "bloom": "3-6",
        "tags": "annual|partial sun|spring|summer|purple|cool season",
        "archetype": true,
        "score": 70.8,
        "reason": "Takes part sun to part shade and moderate water; blooms in early spring, before this one opens; lower at 0.2 m, for the front of the border; purple against orange, for contrast.",
        "penalties": [
          "over-recommended"
        ]
      },
      {
        "slug": "primrose",
        "name": "Primrose",
        "bot": "Primula",
        "genus": "primula",
        "cat": "Perennial",
        "sun": "part-shade",
        "water": "moderate",
        "zones": "3-8",
        "zmin": 3,
        "zmax": 8,
        "h": 0.2,
        "spread": 0.2,
        "bloom": "3-5",
        "tags": "perennial|part shade|spring|yellow|early|shade",
        "archetype": true,
        "score": 68.7,
        "reason": "Shares part shade and moderate water; blooms in early spring, before this one opens; lower at 0.2 m, for the front of the border; yellow sits close to orange on the wheel.",
        "penalties": []
      },
      {
        "slug": "snowdrop",
        "name": "Snowdrop",
        "bot": "Galanthus",
        "genus": "galanthus",
        "cat": "Bulb",
        "sun": "part-shade",
        "water": "moderate",
        "zones": "3-7",
        "zmin": 3,
        "zmax": 7,
        "h": 0.12,
        "spread": 0.08,
        "bloom": "2-3",
        "tags": "bulb|part shade|winter|spring|white|early",
        "archetype": true,
        "score": 68.5,
        "reason": "Shares part shade and moderate water; blooms in late winter, before this one opens; low at 0.12 m, to carpet the ground beneath; its white flowers settle the orange.",
        "penalties": []
      },
      {
        "slug": "windflower",
        "name": "Windflower",
        "bot": "Anemone blanda",
        "genus": "anemone",
        "cat": "Bulb",
        "sun": "part-sun",
        "water": "moderate",
        "zones": "4-8",
        "zmin": 4,
        "zmax": 8,
        "h": 0.15,
        "spread": 0.1,
        "bloom": "3-4",
        "tags": "bulb|partial sun|spring|blue|early",
        "archetype": true,
        "score": 68.5,
        "reason": "Takes part sun to part shade and moderate water; blooms in early spring, before this one opens; low at 0.15 m, to carpet the ground beneath; blue against orange, for contrast.",
        "penalties": []
      },
      {
        "slug": "jacobs-ladder",
        "name": "Jacob's Ladder",
        "bot": "Polemonium",
        "genus": "polemonium",
        "cat": "Perennial",
        "sun": "part-shade",
        "water": "moderate",
        "zones": "3-7",
        "zmin": 3,
        "zmax": 7,
        "h": 0.5,
        "spread": 0.4,
        "bloom": "5-6",
        "tags": "perennial|part shade|spring|summer|blue|shade",
        "archetype": true,
        "score": 68.3,
        "reason": "Shares part shade and moderate water; blooms in late spring, before this one opens; lower at 0.5 m, for the front of the border; both are native plants.",
        "penalties": []
      },
      {
        "slug": "foam-flower",
        "name": "Foam Flower",
        "bot": "Tiarella",
        "genus": "tiarella",
        "cat": "Perennial",
        "sun": "part-shade",
        "water": "moderate",
        "zones": "3-8",
        "zmin": 3,
        "zmax": 8,
        "h": 0.3,
        "spread": 0.4,
        "bloom": "4-6",
        "tags": "perennial|part shade|spring|summer|white|shade|native",
        "archetype": true,
        "score": 68.3,
        "reason": "Shares part shade and moderate water; blooms in mid spring, before this one opens; lower at 0.3 m, for the front of the border; both are native plants.",
        "penalties": []
      },
      {
        "slug": "dogwood-tree",
        "name": "Flowering Dogwood",
        "bot": "Cornus florida",
        "genus": "cornus",
        "cat": "Tree",
        "sun": "part-shade",
        "water": "moderate",
        "zones": "5-9",
        "zmin": 5,
        "zmax": 9,
        "h": 7,
        "spread": 7,
        "bloom": "4-5",
        "tags": "tree|part shade|spring|white|native",
        "archetype": true,
        "score": 62.6,
        "reason": "Shares part shade and moderate water; blooms in mid spring, before this one opens; stands well above at 7 m, a canopy to plant beneath; both are native plants.",
        "penalties": []
      },
      {
        "slug": "bacopa",
        "name": "Bacopa",
        "bot": "Chaenostoma cordatum",
        "genus": "chaenostoma",
        "cat": "Annual",
        "sun": "part-sun",
        "water": "moderate",
        "zones": "9-11",
        "zmin": 9,
        "zmax": 11,
        "h": 0.15,
        "spread": 0.5,
        "bloom": "5-10",
        "tags": "annual|partial sun|spring|summer|fall|white|trailing|container",
        "archetype": true,
        "score": 62.5,
        "reason": "Takes part sun to part shade and moderate water; low at 0.15 m, to carpet the ground beneath; overlaps, then carries the display into mid fall; its white flowers settle the orange.",
        "penalties": []
      }
    ]
  },
  {
    "subject": {
      "slug": "obedient-plant",
      "name": "Obedient Plant",
      "bot": "Physostegia",
      "genus": "physostegia",
      "cat": "Perennial",
      "sun": "full-sun",
      "water": "moderate",
      "zones": "3-9",
      "zmin": 3,
      "zmax": 9,
      "h": 1,
      "spread": 0.5,
      "bloom": "8-9",
      "tags": "perennial|full sun|summer|fall|pink|native",
      "archetype": true
    },
    "candidates": 77,
    "companions": [
      {
        "slug": "snow-in-summer",
        "name": "Snow-in-Summer",
        "bot": "Cerastium tomentosum",
        "genus": "cerastium",
        "cat": "Perennial",
        "sun": "full-sun",
        "water": "low",
        "zones": "3-7",
        "zmin": 3,
        "zmax": 7,
        "h": 0.15,
        "spread": 0.5,
        "bloom": "5-6",
        "tags": "perennial|full sun|spring|summer|white|silver|edging|drought tolerant",
        "archetype": true,
        "score": 63,
        "reason": "Shares full sun and low to moderate water; blooms in late spring, before this one opens; low at 0.15 m, to carpet the ground beneath; evergreen, so the bed keeps its shape through winter.",
        "penalties": [
          "water-differs"
        ]
      },
      {
        "slug": "arborvitae",
        "name": "Arborvitae",
        "bot": "Thuja occidentalis",
        "genus": "thuja",
        "cat": "Conifer",
        "sun": "full-sun",
        "water": "moderate",
        "zones": "3-8",
        "zmin": 3,
        "zmax": 8,
        "h": 6,
        "spread": 1.5,
        "bloom": "",
        "tags": "conifer|full sun|evergreen|columnar|screen|hedge",
        "archetype": true,
        "score": 52.2,
        "reason": "Shares full sun and moderate water; evergreen, so the bed keeps its shape through winter; taller at 6 m, for the layer behind it; both are native plants.",
        "penalties": []
      },
      {
        "slug": "gardenia",
        "name": "Gardenia",
        "bot": "Gardenia jasminoides",
        "genus": "gardenia",
        "cat": "Shrub",
        "sun": "part-sun",
        "water": "high",
        "zones": "8-11",
        "zmin": 8,
        "zmax": 11,
        "h": 1.2,
        "spread": 1.2,
        "bloom": "5-7",
        "tags": "shrub|partial sun|spring|summer|white|fragrant|evergreen",
        "archetype": true,
        "score": 45.7,
        "reason": "Takes full sun to part sun and moderate to high water; blooms in late spring, before this one opens; evergreen, so the bed keeps its shape through winter; a soft colour beside the pink; they only overlap in zones 8 to 9.",
        "penalties": [
          "water-differs",
          "narrow-zone-overlap",
          "over-recommended"
        ]
      },
      {
        "slug": "bee-balm",
        "name": "Bee Balm",
        "bot": "Monarda",
        "genus": "monarda",
        "cat": "Perennial",
        "sun": "full-sun",
        "water": "moderate",
        "zones": "3-9",
        "zmin": 3,
        "zmax": 9,
        "h": 0.9,
        "spread": 0.6,
        "bloom": "7-8",
        "tags": "perennial|full sun|summer|red|pollinator|fragrant",
        "archetype": true,
        "score": 45.5,
        "reason": "Shares full sun and moderate water; opens in midsummer and overlaps into this one's season; both are native plants; red sits close to pink on the wheel.",
        "penalties": []
      },
      {
        "slug": "queen-of-the-prairie",
        "name": "Queen of the Prairie",
        "bot": "Filipendula rubra",
        "genus": "filipendula",
        "cat": "Perennial",
        "sun": "full-sun",
        "water": "high",
        "zones": "3-9",
        "zmin": 3,
        "zmax": 9,
        "h": 1.5,
        "spread": 0.8,
        "bloom": "6-7",
        "tags": "perennial|full sun|summer|pink|native|tall",
        "archetype": true,
        "score": 45.2,
        "reason": "Shares full sun and moderate to high water; blooms in early summer, before this one opens; both are native plants; echoes the pink.",
        "penalties": [
          "water-differs"
        ]
      },
      {
        "slug": "winterberry",
        "name": "Winterberry",
        "bot": "Ilex verticillata",
        "genus": "ilex",
        "cat": "Shrub",
        "sun": "full-sun",
        "water": "high",
        "zones": "3-9",
        "zmin": 3,
        "zmax": 9,
        "h": 2,
        "spread": 2,
        "bloom": "10-12",
        "tags": "shrub|full sun|fall|winter|red|berries|native",
        "archetype": true,
        "score": 45.2,
        "reason": "Shares full sun and moderate to high water; blooms in mid fall as this one finishes; both are native plants; red sits close to pink on the wheel.",
        "penalties": [
          "water-differs"
        ]
      },
      {
        "slug": "blue-oat-grass",
        "name": "Blue Oat Grass",
        "bot": "Helictotrichon sempervirens",
        "genus": "helictotrichon",
        "cat": "Grass",
        "sun": "full-sun",
        "water": "low",
        "zones": "4-9",
        "zmin": 4,
        "zmax": 9,
        "h": 0.7,
        "spread": 0.6,
        "bloom": "6-7",
        "tags": "grass|full sun|summer|blue|evergreen|drought tolerant",
        "archetype": true,
        "score": 45,
        "reason": "Shares full sun and low to moderate water; blooms in early summer, before this one opens; evergreen, so the bed keeps its shape through winter; lower at 0.7 m, for the front of the border; this one spreads, so it will crowd its neighbour in time.",
        "penalties": [
          "spreader-needs-watching",
          "water-differs",
          "over-recommended"
        ]
      },
      {
        "slug": "maiden-grass",
        "name": "Maiden Grass",
        "bot": "Miscanthus sinensis",
        "genus": "miscanthus",
        "cat": "Grass",
        "sun": "full-sun",
        "water": "low",
        "zones": "5-9",
        "zmin": 5,
        "zmax": 9,
        "h": 1.8,
        "spread": 1.2,
        "bloom": "9-10",
        "tags": "grass|full sun|fall|plume|silver|drought tolerant",
        "archetype": true,
        "score": 44.9,
        "reason": "Shares full sun and low to moderate water; overlaps, then carries the display into mid fall; its seed heads stand through winter, for structure and the birds.",
        "penalties": [
          "water-differs"
        ]
      }
    ]
  },
  {
    "subject": {
      "slug": "oregano",
      "name": "Oregano",
      "bot": "Origanum",
      "genus": "origanum",
      "cat": "Herb",
      "sun": "full-sun",
      "water": "low",
      "zones": "4-9",
      "zmin": 4,
      "zmax": 9,
      "h": 0.4,
      "spread": 0.4,
      "bloom": "6-8",
      "tags": "herb|full sun|summer|purple|edible|fragrant|drought tolerant",
      "archetype": true
    },
    "candidates": 172,
    "companions": [
      {
        "slug": "rock-cress",
        "name": "Rock Cress",
        "bot": "Aubrieta",
        "genus": "aubrieta",
        "cat": "Perennial",
        "sun": "full-sun",
        "water": "low",
        "zones": "4-8",
        "zmin": 4,
        "zmax": 8,
        "h": 0.1,
        "spread": 0.4,
        "bloom": "4-5",
        "tags": "perennial|full sun|spring|purple|edging|drought tolerant",
        "archetype": true,
        "score": 71.5,
        "reason": "Shares full sun and low water; blooms in mid spring, before this one opens; both offer pollinator forage, in different months; evergreen, so the bed keeps its shape through winter.",
        "penalties": [
          "over-recommended"
        ]
      },
      {
        "slug": "goldenrod",
        "name": "Goldenrod",
        "bot": "Solidago",
        "genus": "solidago",
        "cat": "Perennial",
        "sun": "full-sun",
        "water": "low",
        "zones": "3-9",
        "zmin": 3,
        "zmax": 9,
        "h": 0.9,
        "spread": 0.5,
        "bloom": "8-10",
        "tags": "perennial|full sun|summer|fall|yellow|pollinator|native|drought tolerant",
        "archetype": true,
        "score": 70.2,
        "reason": "Shares full sun and low water; overlaps, then carries the display into mid fall; both are strong pollinator plants; its seed heads stand through winter, for structure and the birds.",
        "penalties": [
          "over-recommended"
        ]
      },
      {
        "slug": "aster",
        "name": "Aster",
        "bot": "Symphyotrichum",
        "genus": "symphyotrichum",
        "cat": "Perennial",
        "sun": "full-sun",
        "water": "moderate",
        "zones": "3-8",
        "zmin": 3,
        "zmax": 8,
        "h": 0.9,
        "spread": 0.6,
        "bloom": "9-10",
        "tags": "perennial|full sun|fall|purple|pollinator",
        "archetype": true,
        "score": 68,
        "reason": "Shares full sun and low to moderate water; blooms in early fall as this one finishes; both are strong pollinator plants, and they feed in different months; its seed heads stand through winter, for structure and the birds.",
        "penalties": [
          "water-differs",
          "over-recommended"
        ]
      },
      {
        "slug": "rosemary",
        "name": "Rosemary",
        "bot": "Salvia rosmarinus",
        "genus": "salvia",
        "cat": "Herb",
        "sun": "full-sun",
        "water": "low",
        "zones": "7-10",
        "zmin": 7,
        "zmax": 10,
        "h": 1,
        "spread": 0.8,
        "bloom": "3-5",
        "tags": "herb|full sun|spring|blue|fragrant|edible|evergreen|drought tolerant",
        "archetype": true,
        "score": 65,
        "reason": "Shares full sun and low water; blooms in early spring, before this one opens; both are strong pollinator plants, and they feed in different months; evergreen, so the bed keeps its shape through winter.",
        "penalties": [
          "over-recommended"
        ]
      },
      {
        "slug": "lilac",
        "name": "Lilac",
        "bot": "Syringa vulgaris",
        "genus": "syringa",
        "cat": "Shrub",
        "sun": "full-sun",
        "water": "moderate",
        "zones": "3-7",
        "zmin": 3,
        "zmax": 7,
        "h": 3,
        "spread": 2.5,
        "bloom": "4-5",
        "tags": "shrub|full sun|spring|purple|fragrant",
        "archetype": true,
        "score": 55.7,
        "reason": "Shares full sun and low to moderate water; blooms in mid spring, before this one opens; both offer pollinator forage, in different months; stands well above at 3 m, a canopy to plant beneath.",
        "penalties": [
          "water-differs"
        ]
      },
      {
        "slug": "colchicum",
        "name": "Autumn Crocus",
        "bot": "Colchicum",
        "genus": "colchicum",
        "cat": "Bulb",
        "sun": "full-sun",
        "water": "moderate",
        "zones": "4-9",
        "zmin": 4,
        "zmax": 9,
        "h": 0.15,
        "spread": 0.1,
        "bloom": "9-10",
        "tags": "bulb|full sun|fall|purple",
        "archetype": true,
        "score": 55.5,
        "reason": "Shares full sun and low to moderate water; blooms in early fall as this one finishes; both offer pollinator forage, in different months; lower at 0.15 m, for the front of the border.",
        "penalties": [
          "water-differs",
          "over-recommended"
        ]
      },
      {
        "slug": "fountain-grass",
        "name": "Fountain Grass",
        "bot": "Pennisetum alopecuroides",
        "genus": "pennisetum",
        "cat": "Grass",
        "sun": "full-sun",
        "water": "low",
        "zones": "5-9",
        "zmin": 5,
        "zmax": 9,
        "h": 1,
        "spread": 1,
        "bloom": "8-10",
        "tags": "grass|full sun|summer|fall|green|plume|drought tolerant",
        "archetype": true,
        "score": 55.5,
        "reason": "Shares full sun and low water; overlaps, then carries the display into mid fall; its seed heads stand through winter, for structure and the birds; taller at 1 m, for the layer behind it.",
        "penalties": []
      },
      {
        "slug": "pampas-grass",
        "name": "Pampas Grass",
        "bot": "Cortaderia selloana",
        "genus": "cortaderia",
        "cat": "Grass",
        "sun": "full-sun",
        "water": "low",
        "zones": "7-11",
        "zmin": 7,
        "zmax": 11,
        "h": 2.5,
        "spread": 1.5,
        "bloom": "8-10",
        "tags": "grass|full sun|summer|fall|plume|white|drought tolerant",
        "archetype": true,
        "score": 55.5,
        "reason": "Shares full sun and low water; overlaps, then carries the display into mid fall; its seed heads stand through winter, for structure and the birds; stands well above at 2.5 m, a canopy to plant beneath.",
        "penalties": []
      }
    ]
  },
  {
    "subject": {
      "slug": "ornamental-kale",
      "name": "Ornamental Kale",
      "bot": "Brassica oleracea",
      "genus": "brassica",
      "cat": "Annual",
      "sun": "full-sun",
      "water": "moderate",
      "zones": "2-11",
      "zmin": 2,
      "zmax": 11,
      "h": 0.3,
      "spread": 0.4,
      "bloom": "",
      "tags": "annual|full sun|foliage|purple|fall",
      "archetype": true
    },
    "candidates": 185,
    "companions": [
      {
        "slug": "helenium",
        "name": "Sneezeweed",
        "bot": "Helenium",
        "genus": "helenium",
        "cat": "Perennial",
        "sun": "full-sun",
        "water": "moderate",
        "zones": "3-8",
        "zmin": 3,
        "zmax": 8,
        "h": 1,
        "spread": 0.5,
        "bloom": "7-9",
        "tags": "perennial|full sun|summer|fall|orange|pollinator",
        "archetype": true,
        "score": 44.2,
        "reason": "Shares full sun and moderate water; its seed heads stand through winter, for structure and the birds; taller at 1 m, for the layer behind it.",
        "penalties": [
          "over-recommended"
        ]
      },
      {
        "slug": "perennial-sunflower",
        "name": "Perennial Sunflower",
        "bot": "Helianthus",
        "genus": "helianthus",
        "cat": "Perennial",
        "sun": "full-sun",
        "water": "moderate",
        "zones": "4-9",
        "zmin": 4,
        "zmax": 9,
        "h": 1.5,
        "spread": 0.8,
        "bloom": "8-10",
        "tags": "perennial|full sun|summer|fall|yellow|pollinator|native|tall",
        "archetype": true,
        "score": 44.2,
        "reason": "Shares full sun and moderate water; its seed heads stand through winter, for structure and the birds; taller at 1.5 m, for the layer behind it.",
        "penalties": [
          "over-recommended"
        ]
      },
      {
        "slug": "joe-pye-weed",
        "name": "Joe Pye Weed",
        "bot": "Eutrochium",
        "genus": "eutrochium",
        "cat": "Perennial",
        "sun": "full-sun",
        "water": "high",
        "zones": "4-9",
        "zmin": 4,
        "zmax": 9,
        "h": 1.8,
        "spread": 0.9,
        "bloom": "7-9",
        "tags": "perennial|full sun|summer|fall|pink|native|pollinator|tall",
        "archetype": true,
        "score": 42.8,
        "reason": "Shares full sun and moderate to high water; its seed heads stand through winter, for structure and the birds; taller at 1.8 m, for the layer behind it.",
        "penalties": [
          "water-differs"
        ]
      },
      {
        "slug": "feather-reed-grass",
        "name": "Feather Reed Grass",
        "bot": "Calamagrostis × acutiflora",
        "genus": "calamagrostis",
        "cat": "Grass",
        "sun": "full-sun",
        "water": "moderate",
        "zones": "4-9",
        "zmin": 4,
        "zmax": 9,
        "h": 1.5,
        "spread": 0.6,
        "bloom": "6-8",
        "tags": "grass|full sun|summer|green|plume|vertical",
        "archetype": true,
        "score": 41.9,
        "reason": "Shares full sun and moderate water; its seed heads stand through winter, for structure and the birds; taller at 1.5 m, for the layer behind it.",
        "penalties": [
          "over-recommended"
        ]
      },
      {
        "slug": "switchgrass",
        "name": "Switchgrass",
        "bot": "Panicum virgatum",
        "genus": "panicum",
        "cat": "Grass",
        "sun": "full-sun",
        "water": "low",
        "zones": "4-9",
        "zmin": 4,
        "zmax": 9,
        "h": 1.5,
        "spread": 0.8,
        "bloom": "8-10",
        "tags": "grass|full sun|summer|fall|green|plume|native|drought tolerant",
        "archetype": true,
        "score": 40.1,
        "reason": "Shares full sun and low to moderate water; its seed heads stand through winter, for structure and the birds; taller at 1.5 m, for the layer behind it.",
        "penalties": [
          "water-differs",
          "over-recommended"
        ]
      },
      {
        "slug": "boxwood",
        "name": "Boxwood",
        "bot": "Buxus",
        "genus": "buxus",
        "cat": "Shrub",
        "sun": "full-sun",
        "water": "moderate",
        "zones": "5-9",
        "zmin": 5,
        "zmax": 9,
        "h": 1.2,
        "spread": 1.2,
        "bloom": "",
        "tags": "shrub|full sun|foliage|evergreen|hedge",
        "archetype": true,
        "score": 40,
        "reason": "Shares full sun and moderate water; evergreen, so the bed keeps its shape through winter; taller at 1.2 m, for the layer behind it.",
        "penalties": []
      },
      {
        "slug": "fountain-grass",
        "name": "Fountain Grass",
        "bot": "Pennisetum alopecuroides",
        "genus": "pennisetum",
        "cat": "Grass",
        "sun": "full-sun",
        "water": "low",
        "zones": "5-9",
        "zmin": 5,
        "zmax": 9,
        "h": 1,
        "spread": 1,
        "bloom": "8-10",
        "tags": "grass|full sun|summer|fall|green|plume|drought tolerant",
        "archetype": true,
        "score": 39.7,
        "reason": "Shares full sun and low to moderate water; its seed heads stand through winter, for structure and the birds; taller at 1 m, for the layer behind it.",
        "penalties": [
          "water-differs"
        ]
      },
      {
        "slug": "gardenia",
        "name": "Gardenia",
        "bot": "Gardenia jasminoides",
        "genus": "gardenia",
        "cat": "Shrub",
        "sun": "part-sun",
        "water": "high",
        "zones": "8-11",
        "zmin": 8,
        "zmax": 11,
        "h": 1.2,
        "spread": 1.2,
        "bloom": "5-7",
        "tags": "shrub|partial sun|spring|summer|white|fragrant|evergreen",
        "archetype": true,
        "score": 39.3,
        "reason": "Takes full sun to part sun and moderate to high water; evergreen, so the bed keeps its shape through winter; taller at 1.2 m, for the layer behind it.",
        "penalties": [
          "water-differs",
          "over-recommended"
        ]
      }
    ]
  },
  {
    "subject": {
      "slug": "osteospermum",
      "name": "African Daisy",
      "bot": "Osteospermum",
      "genus": "osteospermum",
      "cat": "Annual",
      "sun": "full-sun",
      "water": "moderate",
      "zones": "9-11",
      "zmin": 9,
      "zmax": 11,
      "h": 0.3,
      "spread": 0.3,
      "bloom": "4-6",
      "tags": "annual|full sun|spring|summer|purple",
      "archetype": true
    },
    "candidates": 185,
    "companions": [
      {
        "slug": "joe-pye-weed",
        "name": "Joe Pye Weed",
        "bot": "Eutrochium",
        "genus": "eutrochium",
        "cat": "Perennial",
        "sun": "full-sun",
        "water": "high",
        "zones": "4-9",
        "zmin": 4,
        "zmax": 9,
        "h": 1.8,
        "spread": 0.9,
        "bloom": "7-9",
        "tags": "perennial|full sun|summer|fall|pink|native|pollinator|tall",
        "archetype": true,
        "score": 72.4,
        "reason": "Shares full sun and moderate to high water; blooms in midsummer as this one finishes; both offer pollinator forage, in different months; its seed heads stand through winter, for structure and the birds.",
        "penalties": [
          "water-differs"
        ]
      },
      {
        "slug": "helenium",
        "name": "Sneezeweed",
        "bot": "Helenium",
        "genus": "helenium",
        "cat": "Perennial",
        "sun": "full-sun",
        "water": "moderate",
        "zones": "3-8",
        "zmin": 3,
        "zmax": 8,
        "h": 1,
        "spread": 0.5,
        "bloom": "7-9",
        "tags": "perennial|full sun|summer|fall|orange|pollinator",
        "archetype": true,
        "score": 72.3,
        "reason": "Shares full sun and moderate water; blooms in midsummer as this one finishes; both offer pollinator forage, in different months; its seed heads stand through winter, for structure and the birds.",
        "penalties": [
          "over-recommended"
        ]
      },
      {
        "slug": "false-sunflower",
        "name": "False Sunflower",
        "bot": "Heliopsis",
        "genus": "heliopsis",
        "cat": "Perennial",
        "sun": "full-sun",
        "water": "moderate",
        "zones": "3-9",
        "zmin": 3,
        "zmax": 9,
        "h": 1.2,
        "spread": 0.6,
        "bloom": "7-9",
        "tags": "perennial|full sun|summer|fall|yellow|pollinator|native",
        "archetype": true,
        "score": 71,
        "reason": "Shares full sun and moderate water; blooms in midsummer as this one finishes; both offer pollinator forage, in different months; its seed heads stand through winter, for structure and the birds.",
        "penalties": [
          "over-recommended"
        ]
      },
      {
        "slug": "sunflower",
        "name": "Sunflower",
        "bot": "Helianthus annuus",
        "genus": "helianthus",
        "cat": "Annual",
        "sun": "full-sun",
        "water": "moderate",
        "zones": "none",
        "zmin": null,
        "zmax": null,
        "h": 2,
        "spread": 0.5,
        "bloom": "7-9",
        "tags": "annual|full sun|summer|fall|yellow|tall|pollinator",
        "archetype": true,
        "score": 65.1,
        "reason": "Shares full sun and moderate water; blooms in midsummer as this one finishes; both offer pollinator forage, in different months; its seed heads stand through winter, for structure and the birds.",
        "penalties": [
          "over-recommended"
        ]
      },
      {
        "slug": "passionflower",
        "name": "Passionflower",
        "bot": "Passiflora",
        "genus": "passiflora",
        "cat": "Climber",
        "sun": "full-sun",
        "water": "moderate",
        "zones": "6-9",
        "zmin": 6,
        "zmax": 9,
        "h": 4,
        "spread": 1.5,
        "bloom": "7-9",
        "tags": "climber|full sun|summer|fall|purple|exotic|vine",
        "archetype": true,
        "score": 58.8,
        "reason": "Shares full sun and moderate water; blooms in midsummer as this one finishes; both offer pollinator forage, in different months; echoes the purple.",
        "penalties": []
      },
      {
        "slug": "lavender",
        "name": "Lavender",
        "bot": "Lavandula",
        "genus": "lavandula",
        "cat": "Herb",
        "sun": "full-sun",
        "water": "low",
        "zones": "5-9",
        "zmin": 5,
        "zmax": 9,
        "h": 0.6,
        "spread": 0.6,
        "bloom": "6-8",
        "tags": "herb|full sun|summer|purple|fragrant|pollinator|drought tolerant",
        "archetype": true,
        "score": 56.3,
        "reason": "Shares full sun and low to moderate water; overlaps, then carries the display into late summer; evergreen, so the bed keeps its shape through winter; both offer pollinator forage.",
        "penalties": [
          "water-differs",
          "over-recommended"
        ]
      },
      {
        "slug": "rose-of-sharon",
        "name": "Rose of Sharon",
        "bot": "Hibiscus syriacus",
        "genus": "hibiscus",
        "cat": "Shrub",
        "sun": "full-sun",
        "water": "moderate",
        "zones": "5-9",
        "zmin": 5,
        "zmax": 9,
        "h": 2.5,
        "spread": 1.8,
        "bloom": "7-9",
        "tags": "shrub|full sun|summer|fall|purple",
        "archetype": true,
        "score": 55.5,
        "reason": "Shares full sun and moderate water; blooms in midsummer as this one finishes; stands well above at 2.5 m, a canopy to plant beneath; both offer pollinator forage, in different months.",
        "penalties": []
      },
      {
        "slug": "witch-hazel",
        "name": "Witch Hazel",
        "bot": "Hamamelis",
        "genus": "hamamelis",
        "cat": "Shrub",
        "sun": "part-sun",
        "water": "moderate",
        "zones": "3-8",
        "zmin": 3,
        "zmax": 8,
        "h": 3,
        "spread": 3,
        "bloom": "2-3",
        "tags": "shrub|partial sun|winter|spring|yellow|fragrant|native",
        "archetype": true,
        "score": 53.9,
        "reason": "Takes full sun to part sun and moderate water; blooms in late winter, before this one opens; stands well above at 3 m, a canopy to plant beneath; both offer pollinator forage, in different months.",
        "penalties": [
          "over-recommended"
        ]
      }
    ]
  },
  {
    "subject": {
      "slug": "ostrich-fern",
      "name": "Ostrich Fern",
      "bot": "Matteuccia struthiopteris",
      "genus": "matteuccia",
      "cat": "Fern",
      "sun": "part-shade",
      "water": "high",
      "zones": "3-7",
      "zmin": 3,
      "zmax": 7,
      "h": 1.2,
      "spread": 0.9,
      "bloom": "",
      "tags": "fern|part shade|foliage|shade|native|tall",
      "archetype": true
    },
    "candidates": 24,
    "companions": [
      {
        "slug": "ajuga",
        "name": "Bugleweed",
        "bot": "Ajuga reptans",
        "genus": "ajuga",
        "cat": "Perennial",
        "sun": "part-shade",
        "water": "moderate",
        "zones": "3-9",
        "zmin": 3,
        "zmax": 9,
        "h": 0.15,
        "spread": 0.4,
        "bloom": "4-6",
        "tags": "perennial|part shade|spring|summer|purple|groundcover|shade",
        "archetype": true,
        "score": 53.5,
        "reason": "Shares part shade and moderate to high water; low at 0.15 m, to carpet the ground beneath; evergreen, so the bed keeps its shape through winter.",
        "penalties": [
          "water-differs"
        ]
      },
      {
        "slug": "pachysandra",
        "name": "Pachysandra",
        "bot": "Pachysandra terminalis",
        "genus": "pachysandra",
        "cat": "Perennial",
        "sun": "full-shade",
        "water": "moderate",
        "zones": "4-8",
        "zmin": 4,
        "zmax": 8,
        "h": 0.2,
        "spread": 0.4,
        "bloom": "4-5",
        "tags": "perennial|shade|spring|foliage|groundcover|evergreen",
        "archetype": true,
        "score": 53.5,
        "reason": "Takes part shade to full shade and moderate to high water; lower at 0.2 m, for the front of the border; evergreen, so the bed keeps its shape through winter.",
        "penalties": [
          "water-differs"
        ]
      },
      {
        "slug": "hemlock",
        "name": "Eastern Hemlock",
        "bot": "Tsuga canadensis",
        "genus": "tsuga",
        "cat": "Conifer",
        "sun": "part-shade",
        "water": "moderate",
        "zones": "3-7",
        "zmin": 3,
        "zmax": 7,
        "h": 15,
        "spread": 8,
        "bloom": "",
        "tags": "conifer|part shade|evergreen|native|shade|hedge",
        "archetype": true,
        "score": 46.1,
        "reason": "Shares part shade and moderate to high water; evergreen, so the bed keeps its shape through winter; both are native plants.",
        "penalties": [
          "water-differs"
        ]
      },
      {
        "slug": "lily-of-valley",
        "name": "Lily of the Valley",
        "bot": "Convallaria majalis",
        "genus": "convallaria",
        "cat": "Perennial",
        "sun": "full-shade",
        "water": "moderate",
        "zones": "2-7",
        "zmin": 2,
        "zmax": 7,
        "h": 0.2,
        "spread": 0.3,
        "bloom": "4-5",
        "tags": "perennial|shade|spring|white|fragrant",
        "archetype": true,
        "score": 38.9,
        "reason": "Takes part shade to full shade and moderate to high water; lower at 0.2 m, for the front of the border.",
        "penalties": [
          "water-differs"
        ]
      },
      {
        "slug": "rhododendron",
        "name": "Rhododendron",
        "bot": "Rhododendron",
        "genus": "rhododendron",
        "cat": "Shrub",
        "sun": "part-shade",
        "water": "moderate",
        "zones": "4-8",
        "zmin": 4,
        "zmax": 8,
        "h": 1.8,
        "spread": 1.8,
        "bloom": "5-6",
        "tags": "shrub|part shade|spring|summer|purple",
        "archetype": true,
        "score": 38.5,
        "reason": "Shares part shade and moderate to high water; evergreen, so the bed keeps its shape through winter.",
        "penalties": [
          "water-differs"
        ]
      },
      {
        "slug": "dogwood-tree",
        "name": "Flowering Dogwood",
        "bot": "Cornus florida",
        "genus": "cornus",
        "cat": "Tree",
        "sun": "part-shade",
        "water": "moderate",
        "zones": "5-9",
        "zmin": 5,
        "zmax": 9,
        "h": 7,
        "spread": 7,
        "bloom": "4-5",
        "tags": "tree|part shade|spring|white|native",
        "archetype": true,
        "score": 33.6,
        "reason": "Shares part shade and moderate to high water; taller at 7 m, for the layer behind it; both are native plants.",
        "penalties": [
          "water-differs"
        ]
      },
      {
        "slug": "northern-sea-oats",
        "name": "Northern Sea Oats",
        "bot": "Chasmanthium latifolium",
        "genus": "chasmanthium",
        "cat": "Grass",
        "sun": "part-shade",
        "water": "moderate",
        "zones": "3-8",
        "zmin": 3,
        "zmax": 8,
        "h": 1,
        "spread": 0.6,
        "bloom": "7-9",
        "tags": "grass|part shade|summer|fall|green|native|seed heads|shade",
        "archetype": true,
        "score": 31.7,
        "reason": "Shares part shade and moderate to high water; its seed heads stand through winter, for structure and the birds; both are native plants; this one spreads, so it will crowd its neighbour in time.",
        "penalties": [
          "spreader-needs-watching",
          "water-differs",
          "over-recommended"
        ]
      },
      {
        "slug": "mint",
        "name": "Mint",
        "bot": "Mentha",
        "genus": "mentha",
        "cat": "Herb",
        "sun": "part-sun",
        "water": "high",
        "zones": "3-9",
        "zmin": 3,
        "zmax": 9,
        "h": 0.5,
        "spread": 0.6,
        "bloom": "6-8",
        "tags": "herb|partial sun|summer|purple|edible|fragrant",
        "archetype": true,
        "score": 30.7,
        "reason": "Takes part sun to part shade and high water; lower at 0.5 m, for the front of the border.",
        "penalties": []
      }
    ]
  }
]